imfind/__init__.py
imfind/bin/__init__.py
imfind/bin/imfind.py
imfind/etc/__init__.py
imfind/lib/__init__.py
imfind/lib/helpers.py
imfind/lib/image.py
imfind/lib/image_and_text.py
imfind/lib/test_load_llava.py
imfind-0.0.10.dist-info/METADATA
imfind-0.0.10.dist-info/WHEEL
imfind-0.0.10.dist-info/entry_points.txt
imfind-0.0.10.dist-info/top_level.txt
imfind-0.0.10.dist-info/RECORD
