Metadata-Version: 2.4
Name: imfind
Version: 0.0.10
Summary: Local AI image finder.
Author-email: Ramya Kottapalli <rskottap@gmail.com>
Project-URL: source, https://github.com/rskottap/imfind
Project-URL: download, https://pypi.org/project/imfind/#files
Requires-Dist: pytest
Requires-Dist: twine
Requires-Dist: requests
Requires-Dist: torch
Requires-Dist: transformers
Requires-Dist: easyocr
Requires-Dist: Pillow
Requires-Dist: pillow-heif
Requires-Dist: assure
Requires-Dist: mmry
Requires-Dist: embd
